splitfile/__init__.py
splitfile-2.0.2.dist-info/LICENSE
splitfile-2.0.2.dist-info/METADATA
splitfile-2.0.2.dist-info/WHEEL
splitfile-2.0.2.dist-info/top_level.txt
splitfile-2.0.2.dist-info/RECORD
