Metadata-Version: 2.1
Name: splitfile
Version: 2.0.2
Summary: File like object that splits data across volumes
Home-page: https://github.com/alemigo/splitfile
Author: github.com/alemigo
License: UNKNOWN
Platform: UNKNOWN
Classifier: Programming Language :: Python :: 3
Classifier: License :: OSI Approved :: GNU General Public License v3 (GPLv3)
Classifier: Operating System :: OS Independent
